LICENSE
MANIFEST.in
README.md
requirements.txt
setup.cfg
setup.py
dstore/__init__.py
dstore/values_pb2.py
dstore/elastic/__init__.py
dstore/elastic/elastic_pb2.py
dstore/elastic/elastic_service_pb2.py
dstore/elastic/item/__init__.py
dstore/elastic/item/item_export_pb2.py
dstore/elastic/item/item_get_pb2.py
dstore/elastic/item/item_pb2.py
dstore/elastic/item/item_suggest_pb2.py
dstore/engine/__init__.py
dstore/engine/engine_pb2.py
dstore/engine/engine_service_pb2.py
dstore/engine/procedure_pb2.py
dstore/engine/procedures/__init__.py
dstore/engine/procedures/ac_ChangeActionState_Ad_pb2.py
dstore/engine/procedures/ac_GetActionLogs_Ad_pb2.py
dstore/engine/procedures/ac_GetActionStatusCategs_Ad_pb2.py
dstore/engine/procedures/ac_GetActionStatusValues_Ad_pb2.py
dstore/engine/procedures/ac_GetActions_Ad_pb2.py
dstore/engine/procedures/ac_GetCommandSettingEntry_pb2.py
dstore/engine/procedures/ac_GetCommandSettings_Ad_pb2.py
dstore/engine/procedures/ac_GetCommands_Ad_pb2.py
dstore/engine/procedures/ac_InsertActionLog_Ad_pb2.py
dstore/engine/procedures/ac_InsertAction_Ad_pb2.py
dstore/engine/procedures/ac_ModifyActionStatusValues_Ad_pb2.py
dstore/engine/procedures/ac_ModifyCommandSettings_Ad_pb2.py
dstore/engine/procedures/ac_ModifyCommands_Ad_pb2.py
dstore/engine/procedures/co_CheckStatistics_Ad_pb2.py
dstore/engine/procedures/co_CreateNewCommunityMember_Pu_pb2.py
dstore/engine/procedures/co_CreateNewMessage_Pu_pb2.py
dstore/engine/procedures/co_DeleteCommunityBinary_Ad_pb2.py
dstore/engine/procedures/co_DeleteCommunityBinary_Pu_pb2.py
dstore/engine/procedures/co_DeleteInactiveMembers_Ad_pb2.py
dstore/engine/procedures/co_DeleteMessage_Pu_pb2.py
dstore/engine/procedures/co_DeleteUsersOnlineTime_Ad_pb2.py
dstore/engine/procedures/co_GetBinQuotaInformation_Pu_pb2.py
dstore/engine/procedures/co_GetBinariesOfOneMember_Ad_pb2.py
dstore/engine/procedures/co_GetBinaryCatAccessLevels_pb2.py
dstore/engine/procedures/co_GetBinaryCategories_Ad_pb2.py
dstore_sdk_python.egg-info/PKG-INFO
dstore_sdk_python.egg-info/SOURCES.txt
dstore_sdk_python.egg-info/dependency_links.txt
dstore_sdk_python.egg-info/requires.txt
dstore_sdk_python.egg-info/top_level.txt