Metadata-Version: 1.0
Name: dstore-sdk-python
Version: 1.0.2.5
Summary: dStore SDK for Python lanaguage.
Home-page: http://www.dstore.de
Author: dbap GmbH
Author-email: dstoreio@dbap.de
License: UNKNOWN
Platform: UNKNOWN
